agentor/__init__.py
agentor/a2a.py
agentor/config.py
agentor/embeddings.py
agentor/output_text_formatter.py
agentor/prompts.py
agentor/runtime.py
agentor/skills.py
agentor/tool_search.py
agentor/tracer.py
agentor/type_helper.py
agentor/types.py
agentor/utils.py
agentor/core/__init__.py
agentor/core/agent.py
agentor/core/llm.py
agentor/core/schema.py
agentor/core/tool.py
agentor/durable/__init__.py
agentor/durable/durable_agent.py
agentor/mcp/__init__.py
agentor/mcp/api_router.py
agentor/mcp/proxy.py
agentor/mcp/server.py
agentor/tools/__init__.py
agentor/tools/base.py
agentor/tools/calculator.py
agentor/tools/exa.py
agentor/tools/fetch.py
agentor/tools/git.py
agentor/tools/github.py
agentor/tools/gmail.py
agentor/tools/linkedin.py
agentor/tools/postgres.py
agentor/tools/registry.py
agentor/tools/shell.py
agentor/tools/slack.py
agentor/tools/timezone.py
agentor/tools/weather.py
celesto_sdk/__init__.py
celesto_sdk/a2a.py
celesto_sdk/deployment.py
celesto_sdk/main.py
celesto_sdk/proxy.py
celesto_sdk/sdk/__init__.py
celesto_sdk/sdk/client.py
agentor-0.0.19.dist-info/METADATA
agentor-0.0.19.dist-info/WHEEL
agentor-0.0.19.dist-info/entry_points.txt
agentor-0.0.19.dist-info/licenses/LICENSE
agentor-0.0.19.dist-info/RECORD
