Metadata-Version: 2.4
Name: agentor
Version: 0.0.19
Summary: Fastest way to build, prototype and deploy AI Agents.
Author-email: Aniket Maurya <aniket@celesto.ai>
License-File: LICENSE
Keywords: AI,Agents,Assistant,Hyper-personal,LLMs,OpenAI
Classifier: Development Status :: 4 - Beta
Classifier: Intended Audience :: Developers
Classifier: License :: OSI Approved :: Apache Software License
Requires-Python: >=3.10
Requires-Dist: a2a-sdk>=0.3.10
Requires-Dist: backoff>=2.2.1
Requires-Dist: bm25s>=0.2.14
Requires-Dist: fastapi>=0.120.0
Requires-Dist: fastmcp>=2.7.1
Requires-Dist: google-api-core>=2.25.1
Requires-Dist: google-api-python-client>=2.178.0
Requires-Dist: google-auth-httplib2>=0.2.0
Requires-Dist: google-auth-oauthlib>=1.2.2
Requires-Dist: google-auth>=2.40.3
Requires-Dist: googleapis-common-protos>=1.70.0
Requires-Dist: jinja2>=3.1.6
Requires-Dist: litellm>=1.78.0
Requires-Dist: mcp>=1.16.0
Requires-Dist: openai-agents>=0.3.3
Requires-Dist: openai>=1.97.0
Requires-Dist: pystemmer>=3.0.0
Requires-Dist: python-dotenv>=1.0.0
Requires-Dist: python-frontmatter>=1.1.0
Requires-Dist: pytz>=2024.1
Requires-Dist: rich>=14.0.0
Requires-Dist: superauth>=0.0.1
Requires-Dist: typeguard>=4.4.4
Requires-Dist: typer>=0.20.0
Requires-Dist: uvicorn>=0.37.0
Provides-Extra: all
Requires-Dist: exa-py>=1.0.0; extra == 'all'
Requires-Dist: gitpython>=3.1.0; extra == 'all'
Requires-Dist: psycopg2-binary>=2.9.0; extra == 'all'
Requires-Dist: pygithub>=2.0.0; extra == 'all'
Requires-Dist: slack-sdk>=3.0.0; extra == 'all'
Provides-Extra: exa
Requires-Dist: exa-py>=1.0.0; extra == 'exa'
Provides-Extra: git
Requires-Dist: gitpython>=3.1.0; extra == 'git'
Provides-Extra: github
Requires-Dist: pygithub>=2.0.0; extra == 'github'
Provides-Extra: postgres
Requires-Dist: psycopg2-binary>=2.9.0; extra == 'postgres'
Provides-Extra: slack
Requires-Dist: slack-sdk>=3.0.0; extra == 'slack'
